sdeul/__init__.py
sdeul/api.py
sdeul/cli.py
sdeul/config.py
sdeul/constants.py
sdeul/extraction.py
sdeul/llm.py
sdeul/utility.py
sdeul/validation.py
sdeul-0.2.0.dist-info/METADATA
sdeul-0.2.0.dist-info/WHEEL
sdeul-0.2.0.dist-info/entry_points.txt
sdeul-0.2.0.dist-info/licenses/LICENSE
sdeul-0.2.0.dist-info/RECORD
