Metadata-Version: 2.4
Name: sdeul
Version: 0.2.0
Summary: Structural Data Extractor using LLMs
Project-URL: homepage, https://github.com/dceoy/sdeul
Project-URL: repository, https://github.com/dceoy/sdeul.git
Project-URL: documentation, https://github.com/dceoy/sdeul/blob/main/README.md
Author-email: Daichi Narushima <dceoy@users.noreply.github.com>
Maintainer-email: Daichi Narushima <dceoy@users.noreply.github.com>
License-Expression: AGPL-3.0-or-later
License-File: LICENSE
Keywords: llm
Classifier: Development Status :: 4 - Beta
Classifier: Environment :: Console
Classifier: Operating System :: OS Independent
Classifier: Programming Language :: Python
Classifier: Programming Language :: Python :: 3
Classifier: Topic :: Software Development
Requires-Python: >=3.11
Requires-Dist: boto3-stubs[sts]>=1.35.24
Requires-Dist: fastapi>=0.115.12
Requires-Dist: jsonschema>=4.23.0
Requires-Dist: langchain-anthropic>=0.3.0
Requires-Dist: langchain-aws>=0.2.0
Requires-Dist: langchain-community>=0.3.0
Requires-Dist: langchain-google-genai>=2.1.0
Requires-Dist: langchain-groq>=0.3.0
Requires-Dist: langchain-ollama>=0.3.0
Requires-Dist: langchain-openai>=0.3.0
Requires-Dist: langchain>=0.3.0
Requires-Dist: llama-cpp-python>=0.3.0
Requires-Dist: typer<0.17,>=0.15
Requires-Dist: uvicorn[standard]>=0.32.1
